trame/__init__.py
trame/modules/__init__.py
trame/modules/code.py
trame/widgets/__init__.py
trame/widgets/code.py
trame_code/__init__.py
trame_code/module/__init__.py
trame_code/module/serve/style.css
trame_code/module/serve/trame-code.umd.js
trame_code/module/serve/monacoeditorwork/css.worker.bundle.js
trame_code/module/serve/monacoeditorwork/editor.worker.bundle.js
trame_code/module/serve/monacoeditorwork/html.worker.bundle.js
trame_code/module/serve/monacoeditorwork/json.worker.bundle.js
trame_code/module/serve/monacoeditorwork/ts.worker.bundle.js
trame_code/widgets/__init__.py
trame_code/widgets/code.py
trame_code-1.0.2.dist-info/LICENSE
trame_code-1.0.2.dist-info/METADATA
trame_code-1.0.2.dist-info/WHEEL
trame_code-1.0.2.dist-info/top_level.txt
trame_code-1.0.2.dist-info/RECORD
